{
  "generator-jhipster": {
    "applicationType": "monolith",
    "gitCompany": "",
    "baseName": "jhipsterSampleApplication",
    "packageName": "com.mycompany.myapp",
    "packageFolder": "com/mycompany/myapp",
    "serverPort": 8080,
    "serviceDiscoveryType": false,
    "authenticationType": "jwt",
    "uaaBaseName": "../uaa",
    "cacheProvider": "ehcache",
    "enableHibernateCache": true,
    "websocket": false,
    "databaseType": "sql",
    "devDatabaseType": "h2Disk",
    "prodDatabaseType": "mysql",
    "searchEngine": false,
    "enableSwaggerCodegen": false,
    "messageBroker": false,
    "buildTool": "maven",
    "useSass": true,
    "clientPackageManager": "npm",
    "testFrameworks": [
      "gatling",
      "cucumber"
    ],
    "enableTranslation": true,
    "nativeLanguage": "en",
    "languages": [
      "en"
    ],
    "clientFramework": "angularX",
    "jhiPrefix": "jhi",
    "jhipsterVersion": "6.3.1",
    "jwtSecretKey": "ZmE5M2M4ZWIxZDVkNDAxZTBjNTkwMzkxZTViMjIwNDg0MDBhYzEzZThhNTFhNDAwMWI3ZTE5ODQ1ZWI0MmM5OGE0NjI0NTcxOWVlNjA3Mzk3OWYzMTA4OWVmNTdiNjM0MDhhZTVmMDE4ODE1NTQ5YWE4NTNiNjBmZDUyZGQxNTA=",
    "embeddableLaunchScript": false,
    "clientTheme": "none",
    "entitySuffix": "",
    "dtoSuffix": "DTO",
    "otherModules": [],
    "blueprints": []
  },
  "git-provider": "GitHub",
  "git-company": "oworrob",
  "repository-name": "jhipster-sample-application"
}